bqq/__init__.py
bqq/auth.py
bqq/bq_client.py
bqq/config.py
bqq/const.py
bqq/output.py
bqq/types.py
bqq/data/__init__.py
bqq/data/infos.py
bqq/data/results.py
bqq/data/schemas.py
bqq/service/__init__.py
bqq/service/info_service.py
bqq/service/project_service.py
bqq/service/result_service.py
bqq/service/schema_service.py
bqq/util/__init__.py
bqq/util/bash_util.py
bqq/util/bq_util.py
bqq-0.2.2.dist-info/LICENSE
bqq-0.2.2.dist-info/METADATA
bqq-0.2.2.dist-info/WHEEL
bqq-0.2.2.dist-info/entry_points.txt
bqq-0.2.2.dist-info/top_level.txt
bqq-0.2.2.dist-info/RECORD
